github_markdown.py
github_markdown-1.0.0.dist-info/METADATA
github_markdown-1.0.0.dist-info/RECORD
github_markdown-1.0.0.dist-info/WHEEL
github_markdown-1.0.0.dist-info/top_level.txt
